fs/opener/smbfs.py
fs/smbfs/__init__.py
fs/smbfs/_version.txt
fs/smbfs/file.py
fs/smbfs/smbfs.py
fs/smbfs/utils.py
fs.smbfs-1.0.7.dist-info/COPYING
fs.smbfs-1.0.7.dist-info/METADATA
fs.smbfs-1.0.7.dist-info/WHEEL
fs.smbfs-1.0.7.dist-info/entry_points.txt
fs.smbfs-1.0.7.dist-info/top_level.txt
fs.smbfs-1.0.7.dist-info/zip-safe
fs.smbfs-1.0.7.dist-info/RECORD
